CloudwatchLogger/CloudwatchLogger.py
CloudwatchLogger/__init__.py
SQSLogger/SQSLogger.py
SQSLogger/__init__.py
AWSCloudLogger-0.0.2.dist-info/LICENCE
AWSCloudLogger-0.0.2.dist-info/METADATA
AWSCloudLogger-0.0.2.dist-info/WHEEL
AWSCloudLogger-0.0.2.dist-info/top_level.txt
AWSCloudLogger-0.0.2.dist-info/RECORD
