Metadata-Version: 2.1
Name: AWSCloudLogger
Version: 0.0.2
Summary: Lambda function and Library for writing and reading logs to and from SQS or CloudWatch
Home-page: https://github.com/pentairiot/AWSCloudLogger
Author: PentairIoT
Author-email: pentairiot@gmail.com
License: UNKNOWN
Platform: UNKNOWN
Classifier: Programming Language :: Python :: 3
Classifier: License :: OSI Approved :: Apache Software License
Classifier: Operating System :: OS Independent
Requires-Dist: boto3
